subsets_client/__init__.py
subsets_client/client.py
subsets_client/exceptions.py
subsets_client-0.4.2.dist-info/LICENSE
subsets_client-0.4.2.dist-info/METADATA
subsets_client-0.4.2.dist-info/WHEEL
subsets_client-0.4.2.dist-info/RECORD
