Metadata-Version: 2.3
Name: subsets-client
Version: 0.4.2
Summary: Python client for Subsets data platform
License: MIT
Keywords: data,api,client,statistics,analytics
Author: Subsets Team
Author-email: team@subsets.io
Requires-Python: >=3.11,<4.0
Classifier: Development Status :: 4 - Beta
Classifier: Intended Audience :: Developers
Classifier: License :: OSI Approved :: MIT License
Classifier: Programming Language :: Python :: 3
Classifier: Programming Language :: Python :: 3.11
Classifier: Programming Language :: Python :: 3.12
Classifier: Programming Language :: Python :: 3.13
Classifier: Topic :: Software Development :: Libraries :: Python Modules
Requires-Dist: pandas (>=2.2.0,<3.0.0)
Requires-Dist: pyarrow (>=18.1.0,<19.0.0)
Requires-Dist: pyiceberg (>=0.9.0,<0.10.0)
Requires-Dist: requests (>=2.32.0,<3.0.0)
Project-URL: Documentation, https://docs.subsets.io
Project-URL: Homepage, https://subsets.io
Project-URL: Repository, https://github.com/subsetsio/subsets
